Metadata-Version: 2.1
Name: BAMboozle
Version: 0.5.0
Summary: remove genetic variation from sequencing data
Home-page: https://github.com/sandberg-lab/dataprivacy
Author: Christoph Ziegenhain
Author-email: christoph.ziegenhain@ki.se
License: GPL-3.0-or-later
Platform: UNKNOWN
Classifier: Programming Language :: Python :: 3
Classifier: License :: OSI Approved :: GNU General Public License v3 (GPLv3)
Requires-Python: >=3.6
